anvilfs/__about__.py
anvilfs/__init__.py
anvilfs/anvilfs.py
anvilfs/basefile.py
anvilfs/basefolder.py
anvilfs/baseresource.py
anvilfs/clientrepository.py
anvilfs/drs.py
anvilfs/google.py
anvilfs/hypertext.py
anvilfs/namespace.py
anvilfs/reference.py
anvilfs/tables.py
anvilfs/workloadidentitycredentials.py
anvilfs/workspace.py
anvilfs/workspacebucket.py
fs.anvilfs-0.2.5.dist-info/LICENSE
fs.anvilfs-0.2.5.dist-info/METADATA
fs.anvilfs-0.2.5.dist-info/WHEEL
fs.anvilfs-0.2.5.dist-info/top_level.txt
fs.anvilfs-0.2.5.dist-info/RECORD
