Metadata-Version: 2.1
Name: fs.anvilfs
Version: 0.2.5
Summary: PyFilesystem2 AnVIL plugin
Home-page: https://github.com/anvilproject/fs.anvilfs
Author: the AnVIL project
Author-email: sargentl@ohsu.edu
Classifier: Development Status :: 3 - Alpha
Classifier: Intended Audience :: Developers
Classifier: Topic :: Software Development :: Build Tools
Classifier: License :: OSI Approved :: MIT License
Classifier: Programming Language :: Python :: 3
Classifier: Programming Language :: Python :: 3.5
Classifier: Programming Language :: Python :: 3.6
Classifier: Programming Language :: Python :: 3.7
Classifier: Programming Language :: Python :: 3.8
Classifier: Programming Language :: Python :: 3 :: Only
Requires-Python: >=3.5, <4
License-File: LICENSE
Requires-Dist: firecloud (>=0.16.29)
Requires-Dist: fs
Requires-Dist: google-cloud-storage
Requires-Dist: google-cloud-bigquery
Requires-Dist: gs-chunked-io
Requires-Dist: terra-notebook-utils (<0.12.0,>=0.10.0)
Requires-Dist: getm (<0.1.0,>=0.0.4)
